{
  "kind": "collectionType",
  "collectionName": "articles",
  "info": {
    "name": "Article",
    "description": ""
  },
  "options": {
    "increments": true,
    "timestamps": true,
    "draftAndPublish": true
  },
  "pluginOptions": {},
  "attributes": {
    "content": {
      "type": "text"
    },
    "files": {
      "collection": "file",
      "via": "related",
      "allowedTypes": [
        "images",
        "files",
        "videos"
      ],
      "plugin": "upload",
      "required": false,
      "pluginOptions": {}
    },
    "replies": {
      "via": "article",
      "collection": "reply"
    },
    "user": {
      "plugin": "users-permissions",
      "model": "user"
    }
  }
}
